cper.cpython-311-aarch64-linux-musl.so
cper-0.0.4.data/headers/libcper/BaseTypes.h
cper-0.0.4.data/headers/libcper/Cper.h
cper-0.0.4.data/headers/libcper/common-utils.h
cper-0.0.4.data/headers/libcper/cper-parse-str.h
cper-0.0.4.data/headers/libcper/cper-parse.h
cper-0.0.4.data/headers/libcper/cper-utils.h
cper-0.0.4.data/headers/libcper/generator/cper-generate.h
cper-0.0.4.dist-info/LICENSE
cper-0.0.4.dist-info/METADATA
cper-0.0.4.dist-info/WHEEL
cper-0.0.4.dist-info/RECORD
