Metadata-Version: 2.1
Name: cper
Version: 0.0.4
Summary: Package for decoding CPER values
Author-Email: Ed Tanous <ed@tanous.net>
License: 
Requires-Python: >3.10
